pycallgraph2/__init__.py
pycallgraph2/color.py
pycallgraph2/config.py
pycallgraph2/decorators.py
pycallgraph2/exceptions.py
pycallgraph2/globbing_filter.py
pycallgraph2/grouper.py
pycallgraph2/memory_profiler.py
pycallgraph2/metadata.py
pycallgraph2/pycallgraph.py
pycallgraph2/tracer.py
pycallgraph2/util.py
pycallgraph2/output/__init__.py
pycallgraph2/output/gephi.py
pycallgraph2/output/graphviz.py
pycallgraph2/output/output.py
pycallgraph2/output/pickle.py
pycallgraph2/output/ubigraph.py
pycallgraph2-1.1.3.data/scripts/pycallgraph
pycallgraph2-1.1.3.dist-info/LICENSE
pycallgraph2-1.1.3.dist-info/METADATA
pycallgraph2-1.1.3.dist-info/WHEEL
pycallgraph2-1.1.3.dist-info/top_level.txt
pycallgraph2-1.1.3.dist-info/RECORD
