Metadata-Version: 2.1
Name: pycallgraph2
Version: 1.1.3
Summary: Python Call Graph is a Python module that creates call graph visualizations for Python applications.
Home-page: https://github.com/daneads/pycallgraph2
Author: Dan Eads
License: GNU GPLv2
Platform: UNKNOWN
Classifier: Development Status :: 4 - Beta
Classifier: Intended Audience :: Developers
Classifier: License :: OSI Approved :: GNU General Public License (GPL)
Classifier: Natural Language :: English
Classifier: Operating System :: OS Independent
Classifier: Programming Language :: Python
Classifier: Programming Language :: Python :: 2.7
Classifier: Programming Language :: Python :: 3
Classifier: Programming Language :: Python :: 3.3
Classifier: Topic :: Software Development :: Libraries :: Python Modules
Classifier: Topic :: Software Development :: Testing
Classifier: Topic :: Software Development :: Debuggers
